{
  "mapMarkers": [
    {
      "id": "abraham-map",
      "lastAccessed": 1742565654030,
      "markers": [],
      "overlays": [],
      "shapes": [
        {
          "type": "polyline",
          "color": "#3388FF",
          "vertices": [
            {
              "lat": 31.147520510334438,
              "lng": 34.66735839843751,
              "id": "ID_d85acac9d8ab",
              "targets": {
                "vertexIds": []
              }
            },
            {
              "lat": 31.714660510339733,
              "lng": 34.81567382812501,
              "id": "ID_7b69fae9d9ca",
              "targets": {
                "vertexIds": []
              }
            },
            {
              "lat": 31.58321506275729,
              "lng": 35.26062011718751,
              "id": "ID_6bdbb83a6bca",
              "targets": {
                "vertexIds": []
              }
            },
            {
              "lat": 31.64921675093193,
              "lng": 35.69458007812501,
              "id": "ID_7bc87b4aeaeb",
              "targets": {
                "vertexIds": []
              }
            }
          ],
          "arrows": false,
          "reversed": false
        }
      ],
      "files": [
        "Characters/Abraham.md"
      ]
    }
  ],
  "defaultMarker": {
    "type": "default",
    "iconName": "map-marker",
    "color": "#dddddd",
    "transform": {
      "size": 6,
      "x": 0,
      "y": -2
    }
  },
  "markerIcons": [],
  "color": "#dddddd",
  "lat": 39.983334,
  "long": -82.98333,
  "notePreview": false,
  "layerMarkers": true,
  "previousVersion": "6.0.5",
  "version": {
    "major": 6,
    "minor": 0,
    "patch": 5
  },
  "warnedAboutMapMarker": false,
  "copyOnClick": false,
  "displayMarkerTooltips": "hover",
  "displayOverlayTooltips": true,
  "configDirectory": null,
  "mapViewEnabled": true,
  "mapViewParameters": {},
  "enableDraw": true,
  "defaultUnitType": "imperial",
  "defaultTile": "https://{s}.basemaps.cartocdn.com/rastertiles/voyager/{z}/{x}/{y}.png",
  "defaultTileDark": "https://{s}.basemaps.cartocdn.com/rastertiles/voyager/{z}/{x}/{y}.png",
  "defaultAttribution": "&copy; <a href=\"https://www.openstreetmap.org/copyright\">OpenStreetMap</a> contributors &copy; <a href=\"https://carto.com/attributions\">CARTO</a>",
  "defaultTileSubdomains": "a,b,c,d"
}